HISTORY.rst
LICENSE
MANIFEST.in
README.md
README.rst
setup.cfg
setup.py
tox.ini
docs/Makefile
docs/make.bat
docs/build/doctrees/HISTORY.doctree
docs/build/doctrees/client.doctree
docs/build/doctrees/environment.pickle
docs/build/doctrees/index.doctree
docs/build/doctrees/manager.doctree
docs/build/doctrees/model.doctree
docs/build/doctrees/usage.doctree
docs/build/html/.buildinfo
docs/build/html/HISTORY.html
docs/build/html/client.html
docs/build/html/genindex.html
docs/build/html/index.html
docs/build/html/manager.html
docs/build/html/model.html
docs/build/html/objects.inv
docs/build/html/search.html
docs/build/html/searchindex.js
docs/build/html/usage.html
docs/build/html/_modules/index.html
docs/build/html/_modules/queryset_client.html
docs/build/html/_modules/queryset_client/client.html
docs/build/html/_sources/HISTORY.txt
docs/build/html/_sources/client.txt
docs/build/html/_sources/index.txt
docs/build/html/_sources/manager.txt
docs/build/html/_sources/model.txt
docs/build/html/_sources/usage.txt
docs/build/html/_static/ajax-loader.gif
docs/build/html/_static/basic.css
docs/build/html/_static/comment-bright.png
docs/build/html/_static/comment-close.png
docs/build/html/_static/comment.png
docs/build/html/_static/dialog-note.png
docs/build/html/_static/dialog-seealso.png
docs/build/html/_static/dialog-topic.png
docs/build/html/_static/dialog-warning.png
docs/build/html/_static/doctools.js
docs/build/html/_static/down-pressed.png
docs/build/html/_static/down.png
docs/build/html/_static/epub.css
docs/build/html/_static/file.png
docs/build/html/_static/footerbg.png
docs/build/html/_static/headerbg.png
docs/build/html/_static/ie6.css
docs/build/html/_static/jquery.js
docs/build/html/_static/middlebg.png
docs/build/html/_static/minus.png
docs/build/html/_static/plus.png
docs/build/html/_static/pygments.css
docs/build/html/_static/pyramid.css
docs/build/html/_static/searchtools.js
docs/build/html/_static/transparent.gif
docs/build/html/_static/underscore.js
tastypie_queryset_client.egg-info/PKG-INFO
tastypie_queryset_client.egg-info/SOURCES.txt
tastypie_queryset_client.egg-info/dependency_links.txt
tastypie_queryset_client.egg-info/requires.txt
tastypie_queryset_client.egg-info/top_level.txt